{
  "Resources": [
    {
      "Key": "Genshin Impact",
      "DisplayName": "Genshin Impact",
      "WebdavUrl": "https://assets.hoyotoon.com/s/TQgY4mkTyZEat2b",
      "LocalPath": "Resources/Genshin Impact"
    },
    {
      "Key": "Honkai Impact 3rd",
      "DisplayName": "Honkai Impact 3rd",
      "WebdavUrl": "https://assets.hoyotoon.com/s/Q7KkrB69ny5kTBL",
      "LocalPath": "Resources/Honkai Impact 3rd"
    },
    {
      "Key": "Honkai Star Rail",
      "DisplayName": "Honkai Star Rail",
      "WebdavUrl": "https://assets.hoyotoon.com/s/8RaZzPQyLLEFb7o",
      "LocalPath": "Resources/Honkai Star Rail"
    },
    {
      "Key": "Wuthering Waves",
      "DisplayName": "Wuthering Waves",
      "WebdavUrl": "https://assets.hoyotoon.com/s/Y6o9agnZ7xP84sS",
      "LocalPath": "Resources/Wuthering Waves"
    },
    {
      "Key": "Zenless Zone Zero",
      "DisplayName": "Zenless Zone Zero",
      "WebdavUrl": "https://assets.hoyotoon.com/s/BWBcHTK7qmwTnfd",
      "LocalPath": "Resources/Zenless Zone Zero"
    }
  ],
  "Games": [
    {
      "Key": "Honkai Star Rail",
      "GameProperties": ["_mBloomIntensity0"],
      "DefaultShader": "HoyoToon/Honkai Star Rail/Character/Base",
      "ShaderKeywords": {
        "HoyoToon/Honkai Star Rail/Character/Base": ["_UseMoonHalo"],
        "HoyoToon/Honkai Star Rail/Character/Face": [
          "_FaceMap",
          "_FaceExpression",
          "_LipLineFixMax",
          "_LipLineFixStart",
          "_LipLineFixThrd",
          "_NoseLinePower",
          "_OutlineFixFront",
          "_OutlineFixRange1",
          "_OutlineFixRange2",
          "_OutlineFixRange3",
          "_OutlineFixRange4",
          "_OutlineFixSide",
          "_ExCheekColor"
        ],
        "HoyoToon/Honkai Star Rail/Character/Hair": [
          "_HairBlendOffset",
          "_HairBlendWeight",
          "_HairStencilComp",
          "_HairStencilMask"
        ],
        "HoyoToon/Honkai Star Rail/Character/Transparent": [
          "_Sunglasses",
          "_Android_Debug_ToonSpecular",
          "_BendValue"
        ],
        "HoyoToon/Honkai Star Rail/Character/Crystal": [
          "_ParallaxTex",
          "_ParallaxAlpha",
          "_ParallaxScale"
        ]
      },
      "PropertyConversions": {
        "_Test": "_Test2"
      },
      "Tangents": {
        "Options": ["No Tangents", "Tangent Generation", "Vertex Color"],
        "Status": "Tangent Generation",
        "SkipMeshesContaining": [
          "Test",
          "test",
          "TEST",
          "Test",
          "Testing",
          "TangentIgnore"
        ]
      },
      "TextureMappings": {
        "_Lut2DTex": "LUT_HSR"
      },
      "TextureImportSettings": {
        "NameEquals": {
          "LUT_HSR": {
            "SRGBTexture": false,
            "MipmapEnabled": false,
            "TextureCompression": "Uncompressed"
          }
        },
        "NameContains": {
          "ExpressionMap": {
            "SRGBTexture": false
          },
          "FaceMap": {
            "SRGBTexture": false,
            "MipmapEnabled": false
          },
          "LUT": {
            "SRGBTexture": false,
            "MipmapEnabled": false
          },
          "materialidvalueslut": {
            "SRGBTexture": false,
            "NPOTScale": "None"
          },
          "Stockings": {
            "SRGBTexture": false
          },
          "Warm_Ramp": {
            "SRGBTexture": true,
            "MipmapEnabled": false,
            "TextureCompression": "Uncompressed"
          },
          "Cool_Ramp": {
            "SRGBTexture": true,
            "MipmapEnabled": false,
            "TextureCompression": "Uncompressed"
          }
        },
        "NameEndsWith": {
          "T_Caustic": {
            "SRGBTexture": false
          },
          "Stockings": {
            "SRGBTexture": false
          }
        }
      }
    }
  ]
}
